hierarch/__init__.py
hierarch/internal_functions.py
hierarch/numba_overloads.py
hierarch/power.py
hierarch/resampling.py
hierarch/stats.py
hierarch-1.1.6.dist-info/LICENSE.txt
hierarch-1.1.6.dist-info/METADATA
hierarch-1.1.6.dist-info/WHEEL
hierarch-1.1.6.dist-info/RECORD
