Metadata-Version: 2.1
Name: hierarch
Version: 1.1.6
Summary: Hierarchical hypothesis testing library
Home-page: https://github.com/rishi-kulkarni/hierarch
License: LICENSE.txt
Author: Rishi Kulkarni
Author-email: rishi@kulkarni.science
Requires-Python: >=3.8.1,<3.12
Classifier: License :: OSI Approved :: MIT License
Classifier: License :: Other/Proprietary License
Classifier: Operating System :: OS Independent
Classifier: Programming Language :: Python :: 3
Classifier: Programming Language :: Python :: 3.9
Classifier: Programming Language :: Python :: 3.10
Classifier: Programming Language :: Python :: 3.11
Requires-Dist: numba (>=0.57,<0.58)
Requires-Dist: pandas (>=1.5.3,<3.0.0)
Requires-Dist: scipy (>=1.10.0,<2.0.0)
